drag_and_drop_v2/__init__.py
drag_and_drop_v2/compat.py
drag_and_drop_v2/default_data.py
drag_and_drop_v2/drag_and_drop_v2.py
drag_and_drop_v2/utils.py
drag_and_drop_v2/public/css/drag_and_drop.css
drag_and_drop_v2/public/css/drag_and_drop_edit.css
drag_and_drop_v2/public/img/triangle.png
drag_and_drop_v2/public/js/drag_and_drop.js
drag_and_drop_v2/public/js/drag_and_drop_edit.js
drag_and_drop_v2/public/js/translations/ar/text.js
drag_and_drop_v2/public/js/translations/de/text.js
drag_and_drop_v2/public/js/translations/en/text.js
drag_and_drop_v2/public/js/translations/eo/text.js
drag_and_drop_v2/public/js/translations/es_419/text.js
drag_and_drop_v2/public/js/translations/fr/text.js
drag_and_drop_v2/public/js/translations/he/text.js
drag_and_drop_v2/public/js/translations/hi/text.js
drag_and_drop_v2/public/js/translations/it/text.js
drag_and_drop_v2/public/js/translations/ja/text.js
drag_and_drop_v2/public/js/translations/ko/text.js
drag_and_drop_v2/public/js/translations/nl/text.js
drag_and_drop_v2/public/js/translations/pl/text.js
drag_and_drop_v2/public/js/translations/pt_BR/text.js
drag_and_drop_v2/public/js/translations/pt_PT/text.js
drag_and_drop_v2/public/js/translations/ru/text.js
drag_and_drop_v2/public/js/translations/tr/text.js
drag_and_drop_v2/public/js/translations/zh_CN/text.js
drag_and_drop_v2/public/js/vendor/handlebars-v1.1.2.js
drag_and_drop_v2/public/js/vendor/virtual-dom-1.3.0.min.js
drag_and_drop_v2/public/themes/apros.css
drag_and_drop_v2/templates/html/drag_and_drop.html
drag_and_drop_v2/templates/html/drag_and_drop_edit.html
drag_and_drop_v2/templates/html/js_templates.html
drag_and_drop_v2/translations/__init__.py
drag_and_drop_v2/translations/config.yaml
drag_and_drop_v2/translations/settings.py
xblock_drag_and_drop_v2-5.0.3.dist-info/licenses/LICENSE
xblock_drag_and_drop_v2-5.0.3.dist-info/METADATA
xblock_drag_and_drop_v2-5.0.3.dist-info/WHEEL
xblock_drag_and_drop_v2-5.0.3.dist-info/entry_points.txt
xblock_drag_and_drop_v2-5.0.3.dist-info/top_level.txt
xblock_drag_and_drop_v2-5.0.3.dist-info/RECORD
