Metadata-Version: 2.4
Name: xblock-drag-and-drop-v2
Version: 5.0.3
Summary: XBlock - Drag-and-Drop v2
Home-page: https://github.com/openedx/xblock-drag-and-drop-v2
Classifier: Programming Language :: Python
Classifier: Programming Language :: Python :: 3.11
Classifier: Programming Language :: Python :: 3.12
Classifier: Framework :: Django
Classifier: Framework :: Django :: 4.2
Classifier: Framework :: Django :: 5.2
Requires-Python: >=3.11
License-File: LICENSE
Requires-Dist: XBlock[django]
Requires-Dist: bleach[css]
Requires-Dist: django-statici18n
Dynamic: classifier
Dynamic: description
Dynamic: description-content-type
Dynamic: home-page
Dynamic: license-file
Dynamic: requires-dist
Dynamic: requires-python
Dynamic: summary
